MANIFEST.in
setup.cfg
setup.py
pybitcoin/__init__.py
pybitcoin/address.py
pybitcoin/b58check.py
pybitcoin/constants.py
pybitcoin/errors.py
pybitcoin/formatcheck.py
pybitcoin/hash.py
pybitcoin/keypair.py
pybitcoin/merkle.py
pybitcoin/privatekey.py
pybitcoin/publickey.py
pybitcoin/wallet.py
pybitcoin.egg-info/PKG-INFO
pybitcoin.egg-info/SOURCES.txt
pybitcoin.egg-info/dependency_links.txt
pybitcoin.egg-info/not-zip-safe
pybitcoin.egg-info/pbr.json
pybitcoin.egg-info/requires.txt
pybitcoin.egg-info/top_level.txt
pybitcoin/passphrases/__init__.py
pybitcoin/passphrases/english_words.py
pybitcoin/passphrases/legacy.py
pybitcoin/passphrases/passphrase.py
pybitcoin/rpc/__init__.py
pybitcoin/rpc/bitcoind_client.py
pybitcoin/rpc/config.py
pybitcoin/rpc/namecoind_client.py
pybitcoin/rpc/namecoind_cluster.py
pybitcoin/services/__init__.py
pybitcoin/services/bitcoind.py
pybitcoin/services/blockchain_client.py
pybitcoin/services/blockchain_info.py
pybitcoin/services/blockcypher.py
pybitcoin/services/chain_com.py
pybitcoin/transactions/__init__.py
pybitcoin/transactions/network.py
pybitcoin/transactions/opcodes.py
pybitcoin/transactions/outputs.py
pybitcoin/transactions/scripts.py
pybitcoin/transactions/serialize.py
pybitcoin/transactions/utils.py