Metadata-Version: 1.1
Name: pybitcoin
Version: 0.9.9
Summary: Library for Bitcoin & other cryptocurrencies. Tools are provided for blockchain transactions, RPC calls, and private keys, public keys, and addresses.
Home-page: https://github.com/blockstack/pybitcoin
Author: Blockstack Developers
Author-email: hello@onename.com
License: MIT
Keywords: bitcoin btc litecoin namecoin dogecoin cryptocurrency
Platform: UNKNOWN
Classifier: Intended Audience :: Developers
Classifier: License :: OSI Approved :: MIT License
Classifier: Operating System :: OS Independent
Classifier: Programming Language :: Python
Classifier: Topic :: Internet
Classifier: Topic :: Security :: Cryptography
Classifier: Topic :: Software Development :: Libraries :: Python Modules
